faststream_deadline_propagation/__init__.py
faststream_deadline_propagation/countdown.py
faststream_deadline_propagation/defaults.py
faststream_deadline_propagation/exceptions/__init__.py
faststream_deadline_propagation/exceptions/deadline_occurred.py
faststream_deadline_propagation/middlewares/__init__.py
faststream_deadline_propagation/middlewares/process.py
faststream_deadline_propagation/middlewares/publish.py
faststream_deadline_propagation-0.1.2.dist-info/METADATA
faststream_deadline_propagation-0.1.2.dist-info/WHEEL
faststream_deadline_propagation-0.1.2.dist-info/RECORD
