Metadata-Version: 2.1
Name: faststream-deadline-propagation
Version: 0.1.2
Summary: A middleware for the FastStream framework that provides deadline-propagation in Remote Procedure Call requests
Home-page: https://github.com/ulbwa/faststream-deadline-propagation
Author: ульба
Author-email: ulbwa@icloud.com
Requires-Python: >=3.11,<4.0
Classifier: Programming Language :: Python :: 3
Classifier: Programming Language :: Python :: 3.11
Classifier: Programming Language :: Python :: 3.12
Requires-Dist: faststream (>=0.5.18,<0.6.0)
Project-URL: Repository, https://github.com/ulbwa/faststream-deadline-propagation
